{
  "food": {
    "Bites": [
      {
        "name": "Pretzel Bites",
        "description": "Warm, soft pretzel bites with our own beer cheese",
        "price": 8.00,
        "image": {
          "asset": {
            "url": "/images/food/pretzel_bites.jpg"
          }
        }
      },
      {
        "name": "Chips ’n Guac",
        "description": "Housemade guacamole with tortilla chips and salsa",
        "price": 10.00,
        "image": {
          "asset": {
            "url": "/images/food/chips.jpg"
          }
        }
      }
    ],

    "Handhelds & Wraps": [
      {
        "name": "Chicken Salad Wrap",
        "description": "Cranberry chicken salad with romaine on a wrap. Served with chips and a pickle.",
        "price": 12.00
      },
      {
        "name": "Lobster Roll",
        "description": "Fresh, sweet lobster meat served on a buttered roll with chips and liquid butter.",
        "priceOptions": [
          { "label": "Single", "price": 20.00 },
          { "label": "Two Rolls", "price": 30.00 }
        ],
        "image": {
          "asset": {
            "url": "/images/food/lobster.jpg"
          }
        }
      }
    ],

    "Classics & Extras": [
      {
        "name": "Hot Dog",
        "description": "Cooked to perfection. Condiments of your choice. Served on a roll with chips and a pickle.",
        "price": 6.00,
        "image": {
          "asset": {
            "url": "/images/food/hotdog.jpg"
          }
        }
      },
      {
        "name": "Chicken Quesadilla",
        "description": "Served with salsa and sour cream. Add Guac + $2",
        "price": 11.00
      }
    ]
  },
  
   "drink": {
    "Classic Cocktails": [
      {
        "name": "Aperol Spritz",
        "description": "Prosecco, Aperol, soda water and an orange wedge",
        "price": 14.00
      },
      {
        "name": "Orange Crush",
        "description": "Absolut Mandrin, triple sec, fresh squeezed OJ, topped with Sprite",
        "price": 14.00,
        "image": "/images/orangedrink.jpeg"
      },
      {
        "name": "Margarita",
        "description": "Hornitos Plata, orange liqueur, fresh squeezed lime juice and agave",
        "price": 14.00,
        "note": "Make it a Spicy Marg with Fiero habanero tequila. Tajin rim available."
      },
      {
        "name": "Paloma",
        "description": "Hornitos Plata, fresh squeezed grapefruit juice, fresh squeezed lime juice, agave",
        "price": 14.00,
        "note": "Make it a Spicy Paloma with Fiero habanero tequila. Tajin rim available.",
        "image": "/images/paloma.jpeg"

      },
      {
        "name": "Mojito",
        "description": "Bacardi Superior, fresh lime juice, mint, simple syrup, topped with club soda",
        "price": 14.00,
        "note": "Sub for a Coconut Mojito"
      },
      {
        "name": "Painkiller",
        "description": "Pusser’s Navy Rum, cream of coconut, fresh squeezed OJ, pineapple juice and nutmeg",
        "price": 14.00
      }
    ],
    "Signature Cocktails": [
      {
        "name": "935 Espresso Martini",
        "description": "Absolut Vanilla, NOBL espresso, Amarula, Kahlua",
        "price": 14.00
      },
      {
        "name": "Cinnamon Rainbows Blueberry Lemonade",
        "description": "Absolut Citron, blueberry syrup, fresh squeezed lemonade",
        "price": 14.00,
        "image": "/images/berrydrink.jpeg"
      },
      {
        "name": "Boat Rocker",
        "description": "Jim Beam Peach, fresh squeezed lemonade, NOBL iced tea",
        "price": 14.00
        
      },
      {
        "name": "Cucumber Watermelon Fizz",
        "description": "Effen Cucumber, watermelon puree, fresh squeezed lime juice, soda water",
        "price": 14.00
      },
      {
        "name": "High Street Punch",
        "description": "White, dark, and coconut rums mixed with pineapple, fresh squeezed OJ and a splash of grenadine",
        "price": 14.00
      },
      {
        "name": "Cinnamon Rainbows Blueberry Lemonade",
        "description": "Absolut Citron, fresh squeezed lemonade, blueberry syrup",
        "price": 14.00
      },
      {
        "name": "Lupo's Last Call",
        "description": "1800 Coconut, triple sec, cream of coconut, pineapple juice, fresh squeezed lime juice, and agave",
        "price": 14.00
      }
    ],
    "Brews": [
  { "name": "Budweiser", "price": 5.00 },
  { "name": "Bud Light", "price": 5.00 },
  { "name": "Coors Light", "price": 5.00 },
  { "name": "Michelob Ultra", "price": 5.00 },
  { "name": "Athletic Brewing N/A Cerveza", "price": 5.00 },
  { "name": "Allagash White", "price": 6.00 },
  { "name": "Corona Extra", "price": 6.00 },
  { "name": "Kona Big Wave", "price": 6.00 },
  { "name": "Landshark Island Lager", "price": 6.00 },
  { "name": "Modelo", "price": 6.00 },
  { "name": "Sam Adams Seasonal", "price": 6.00 },
  { "name": "Tuckerman Pale Ale", "price": 8.00 },
  { "name": "Lawsons Sip of Sunshine IPA", "price": 8.00 },
  { "name": "Maine Lunch IPA", "price": 14.00 }
],

"Wine": [
  { "name": "Prosecco", "price": 11.00, "type": "Sparkling" },
  { "name": "Rosé", "price": 11.00, "type": "Rosé" },
  { "name": "Pinot Grigio", "price": 11.00, "type": "White" },
  { "name": "Sauvignon Blanc", "price": 12.00, "type": "White" },
  { "name": "Chardonnay", "price": 12.00, "type": "White" },
  { "name": "Pinot Noir", "price": 12.00, "type": "Red" },
  { "name": "Cabernet Sauvignon", "price": 12.00, "type": "Red" }
],

"Seltzers & Beyond": [
  { "name": "Fresh Squeezed Lemonade", "price": 6.00 },
  { "name": "NOBL Iced Tea", "price": 5.00 },
  { "name": "NUTRL Orange", "price": 7.00 },
  { "name": "NUTRL Pineapple", "price": 7.00 },
  { "name": "Suncruiser Iced Tea", "price": 7.00 },
  { "name": "Suncruiser Iced Tea Lemonade", "price": 7.00 },
  { "name": "Suncruiser Pink Lemonade", "price": 7.00 }
]

  }
}